{
    "v": "5.9.6",
    "fr": 29.9700012207031,
    "ip": 0,
    "op": 120,
    "w": 800,
    "h": 600,
    "nm": "Comp 1",
    "ddd": 0,
    "assets": [],
    "layers": [
        {
            "ddd": 0,
            "ind": 1,
            "ty": 4,
            "nm": "Shape Layer 1",
            "sr": 1,
            "ks": {
                "o": {
                    "a": 0,
                    "k": 100,
                    "ix": 11
                },
                "r": {
                    "a": 0,
                    "k": 0,
                    "ix": 10
                },
                "p": {
                    "a": 0,
                    "k": [
                        400,
                        300,
                        0
                    ],
                    "ix": 2
                },
                "a": {
                    "a": 0,
                    "k": [
                        0,
                        0,
                        0
                    ],
                    "ix": 1
                },
                "s": {
                    "a": 0,
                    "k": [
                        100,
                        100,
                        100
                    ],
                    "ix": 6
                }
            },
            "ao": 0,
            "shapes": [
                {
                    "ty": "gr",
                    "it": [
                        {
                            "ind": 0,
                            "ty": "sh",
                            "ix": 1,
                            "ks": {
                                "a": 0,
                                "k": {
                                    "i": [
                                        [
                                            0,
                                            0
                                        ],
                                        [
                                            0,
                                            0
                                        ],
                                        [
                                            0,
                                            0
                                        ],
                                        [
                                            0,
                                            0
                                        ],
                                        [
                                            -44.183,
                                            0
                                        ],
                                        [
                                            0,
                                            0
                                        ],
                                        [
                                            0,
                                            -76.524
                                        ],
                                        [
                                            0,
                                            0
                                        ],
                                        [
                                            0,
                                            0
                                        ],
                                        [
                                            0,
                                            0
                                        ]
                                    ],
                                    "o": [
                                        [
                                            0,
                                            0
                                        ],
                                        [
                                            0,
                                            0
                                        ],
                                        [
                                            0,
                                            0
                                        ],
                                        [
                                            44.183,
                                            0
                                        ],
                                        [
                                            0,
                                            0
                                        ],
                                        [
                                            0,
                                            76.524
                                        ],
                                        [
                                            0,
                                            0
                                        ],
                                        [
                                            0,
                                            0
                                        ],
                                        [
                                            0,
                                            0
                                        ],
                                        [
                                            0,
                                            0
                                        ]
                                    ],
                                    "v": [
                                        [
                                            -190.917,
                                            41.667
                                        ],
                                        [
                                            -190.917,
                                            -25
                                        ],
                                        [
                                            -111.458,
                                            -25
                                        ],
                                        [
                                            -111.458,
                                            -104.479
                                        ],
                                        [
                                            -31.917,
                                            -104.479
                                        ],
                                        [
                                            -31.917,
                                            -181.25
                                        ],
                                        [
                                            47.542,
                                            -181.25
                                        ],
                                        [
                                            165.708,
                                            -63.083
                                        ],
                                        [
                                            165.708,
                                            41.667
                                        ],
                                        [
                                            -190.917,
                                            41.667
                                        ]
                                    ],
                                    "c": true
                                }
                            },
                            "nm": "Path 1",
                            "mn": "ADBE Vector Shape - Group",
                            "hd": false
                        },
                        {
                            "ty": "fl",
                            "c": {
                                "a": 0,
                                "k": [
                                    0.81568627451,
                                    0.81568627451,
                                    0.81568627451,
                                    1
                                ],
                                "ix": 4
                            },
                            "o": {
                                "a": 0,
                                "k": 100,
                                "ix": 5
                            },
                            "r": 1,
                            "bm": 0,
                            "nm": "Fill 1",
                            "mn": "ADBE Vector Graphic - Fill",
                            "hd": false
                        }
                    ],
                    "nm": "Shape 1",
                    "np": 2,
                    "cix": 2,
                    "bm": 0,
                    "ix": 1,
                    "mn": "ADBE Vector Group",
                    "hd": false
                }
            ],
            "ip": 0,
            "op": 120,
            "st": 0,
            "bm": 0
        },
        {
            "ddd": 0,
            "ind": 2,
            "ty": 4,
            "nm": "Star 1",
            "sr": 1,
            "ks": {
                "o": {
                    "a": 0,
                    "k": 100,
                    "ix": 11
                },
                "r": {
                    "a": 0,
                    "k": 0,
                    "ix": 10
                },
                "p": {
                    "a": 0,
                    "k": [
                        400,
                        300,
                        0
                    ],
                    "ix": 2
                },
                "a": {
                    "a": 0,
                    "k": [
                        0,
                        0,
                        0
                    ],
                    "ix": 1
                },
                "s": {
                    "a": 0,
                    "k": [
                        100,
                        100,
                        100
                    ],
                    "ix": 6
                }
            },
            "ao": 0,
            "shapes": [
                {
                    "ty": "gr",
                    "it": [
                        {
                            "ty": "ps",
                            "d": 1,
                            "s": 1,
                            "np": 6,
                            "p": {
                                "a": 0,
                                "k": [
                                    -111.458,
                                    100
                                ],
                                "ix": 2
                            },
                            "r": {
                                "a": 0,
                                "k": 0,
                                "ix": 3
                            },
                            "or": {
                                "a": 0,
                                "k": 25,
                                "ix": 4
                            },
                            "os": {
                                "a": 0,
                                "k": 100,
                                "ix": 5
                            },
                            "ir": {
                                "a": 0,
                                "k": 12.5,
                                "ix": 6
                            },
                            "is": {
                                "a": 0,
                                "k": 100,
                                "ix": 7
                            },
                            "nm": "Polystar Path 1",
                            "mn": "ADBE Vector Shape - Star",
                            "hd": false
                        },
                        {
                            "ty": "fl",
                            "c": {
                                "a": 0,
                                "k": [
                                    1,
                                    1,
                                    1,
                                    1
                                ],
                                "ix": 4
                            },
                            "o": {
                                "a": 0,
                                "k": 100,
                                "ix": 5
                            },
                            "r": 1,
                            "bm": 0,
                            "nm": "Fill 1",
                            "mn": "ADBE Vector Graphic - Fill",
                            "hd": false
                        }
                    ],
                    "nm": "Polystar 1",
                    "np": 2,
                    "cix": 2,
                    "bm": 0,
                    "ix": 1,
                    "mn": "ADBE Vector Group",
                    "hd": false
                }
            ],
            "ip": 0,
            "op": 120,
            "st": 0,
            "bm": 0
        },
        {
            "ddd": 0,
            "ind": 3,
            "ty": 4,
            "nm": "Star 2",
            "sr": 1,
            "ks": {
                "o": {
                    "a": 0,
                    "k": 100,
                    "ix": 11
                },
                "r": {
                    "a": 0,
                    "k": 0,
                    "ix": 10
                },
                "p": {
                    "a": 0,
                    "k": [
                        400,
                        300,
                        0
                    ],
                    "ix": 2
                },
                "a": {
                    "a": 0,
                    "k": [
                        0,
                        0,
                        0
                    ],
                    "ix": 1
                },
                "s": {
                    "a": 0,
                    "k": [
                        100,
                        100,
                        100
                    ],
                    "ix": 6
                }
            },
            "ao": 0,
            "shapes": [
                {
                    "ty": "gr",
                    "it": [
                        {
                            "ty": "ps",
                            "d": 1,
                            "s": 1,
                            "np": 6,
                            "p": {
                                "a": 0,
                                "k": [
                                    47.542,
                                    100
                                ],
                                "ix": 2
                            },
                            "r": {
                                "a": 0,
                                "k": 0,
                                "ix": 3
                            },
                            "or": {
                                "a": 0,
                                "k": 25,
                                "ix": 4
                            },
                            "os": {
                                "a": 0,
                                "k": 100,
                                "ix": 5
                            },
                            "ir": {
                                "a": 0,
                                "k": 12.5,
                                "ix": 6
                            },
                            "is": {
                                "a": 0,
                                "k": 100,
                                "ix": 7
                            },
                            "nm": "Polystar Path 1",
                            "mn": "ADBE Vector Shape - Star",
                            "hd": false
                        },
                        {
                            "ty": "fl",
                            "c": {
                                "a": 0,
                                "k": [
                                    1,
                                    1,
                                    1,
                                    1
                                ],
                                "ix": 4
                            },
                            "o": {
                                "a": 0,
                                "k": 100,
                                "ix": 5
                            },
                            "r": 1,
                            "bm": 0,
                            "nm": "Fill 1",
                            "mn": "ADBE Vector Graphic - Fill",
                            "hd": false
                        }
                    ],
                    "nm": "Polystar 1",
                    "np": 2,
                    "cix": 2,
                    "bm": 0,
                    "ix": 1,
                    "mn": "ADBE Vector Group",
                    "hd": false
                }
            ],
            "ip": 0,
            "op": 120,
            "st": 0,
            "bm": 0
        }
    ],
    "markers": []
}